scann_ascii/__init__.py
scann_ascii/pipeline.py
scann_ascii/utils.py
scann_ascii-0.0.3.dist-info/LICENSE
scann_ascii-0.0.3.dist-info/METADATA
scann_ascii-0.0.3.dist-info/WHEEL
scann_ascii-0.0.3.dist-info/top_level.txt
scann_ascii-0.0.3.dist-info/RECORD
