Metadata-Version: 2.1
Name: scann-ascii
Version: 0.0.3
Summary: scann ascii
Author: Happy Puppy
Author-email: happy.puppy@gmail.com
Classifier: Programming Language :: Python :: 3
Classifier: License :: OSI Approved :: MIT License
Classifier: Operating System :: OS Independent
Requires-Python: >=3.7
License-File: LICENSE
